pc_multiplexer.v
//---------------------------------------------------------------------------
// Multiplexer for Program Counter
//  Selects between 2 32-bit inputs: either the previous value incremented by
//  4, or the jump address.
//---------------------------------------------------------------------------

module pc_multiplexer
(
output reg[31:0] PC,
input wire[31:0] immediate,
input wire[25:0] JumpAddress,
input wire[31:0] regRs,
input clk,
input[1:0] S
);
reg[31:0] temp;
reg[31:0] mux_out;
reg[31:0] nextPC;

initial PC <= 0;

always @(nextPC,JumpAddress,immediate,regRs,S) begin
  if (S == 2'd0) begin
    mux_out <= nextPC;
  end
  else if (S == 2'd1)begin  //jump
    mux_out[27:2] <= JumpAddress;
    mux_out[31:28] <= nextPC[31:28];
    mux_out[1:0] <= 0;
  end
  else if (S == 2'd2)begin  //branch
    mux_out = immediate+nextPC;
  end
  else begin
    mux_out <= regRs;
  end
  nextPC <= PC+4;
end

always @(posedge clk) begin
  PC = mux_out;
  nextPC = PC+4;
end
endmodule

programcounter.t.v
//---------------------------------------------------------------------------
// Test Bench for the Program Counter
//---------------------------------------------------------------------------

`timescale 1 ns / 1 ps
`include "pc_multiplexer.v"

module testPC();
wire[31:0] PC;
reg[15:0] immediate;
reg[25:0] jumpaddress;
reg[31:0] regRs;
reg clk;
reg[1:0] S;

  pc_multiplexer pc (.PC(PC), .immediate(immediate), .JumpAddress(jumpaddress), .regRs(regRs), .clk(clk), .S(S));

initial clk = 0;
always #200 clk = !clk;

  initial begin

  $dumpfile("pc.vcd");
  $dumpvars;
    #400
    immediate = 32'd10; jumpaddress = 26'd20; regRs = 32'd0; S = 2'd3; #210
    if (PC !== 32'd0) begin
    $display("initialization failed");
    end

    #190
    immediate = 32'd10; jumpaddress = 26'd20; regRs = 32'd0; S = 2'd0; #210
    if (PC !== 32'd4) begin
    $display("first increment failed");
    end

    #190
    immediate = 32'd10; jumpaddress = 26'd20; regRs = 32'd0; S = 2'd0; #210
    if (PC !== 32'd8) begin
    $display("second increment failed");
    end

    #190
    immediate = 32'd10; jumpaddress = 26'd20; regRs = 32'd0; S = 2'd0; #210
    if (PC !== 32'd12) begin
    $display("third increment failed");
    end

    #190
    immediate = 32'd10; jumpaddress = 26'd20; regRs = 32'd30; S = 2'd3; #210
    if (PC !== 32'd30) begin
    $display("regRs failed");
    end
    #200 $finish;
  end

  endmodule

pc.vcd
$date
	Thu Nov  1 18:56:45 2018
$end
$version
	Icarus Verilog
$end
$timescale
	1ps
$end
$scope module testPC $end
$var wire 32 ! PC [31:0] $end
$var reg 2 " S [1:0] $end
$var reg 1 # clk $end
$var reg 16 $ immediate [15:0] $end
$var reg 26 % jumpaddress [25:0] $end
$var reg 32 & regRs [31:0] $end
$scope module pc $end
$var wire 26 ' JumpAddress [25:0] $end
$var wire 2 ( S [1:0] $end
$var wire 1 # clk $end
$var wire 32 ) immediate [31:0] $end
$var wire 32 * regRs [31:0] $end
$var reg 32 + PC [31:0] $end
$var reg 32 , mux_out [31:0] $end
$var reg 32 - nextPC [31:0] $end
$upscope $end
$upscope $end
$enddefinitions $end
#0
$dumpvars
bx -
bx ,
bx +
bx *
b0xxxxxxxxxxxxxxxx )
bx (
bx '
bx &
bx %
bx $
0#
bx "
bx !
$end
#200000
1#
#400000
b0 ,
0#
b11 "
b11 (
b0 &
b0 *
b10100 %
b10100 '
b1010 )
b1010 $
#600000
b100 -
b0 !
b0 +
1#
#800000
b100 ,
b0 "
b0 (
0#
#1000000
b1000 ,
b1000 -
b100 !
b100 +
1#
#1200000
0#
#1400000
b1100 ,
b1100 -
b1000 !
b1000 +
1#
#1600000
0#
#1800000
b10000 ,
b10000 -
b1100 !
b1100 +
1#
#2000000
b11110 ,
b11 "
b11 (
b11110 &
b11110 *
0#
#2200000
b100010 -
b11110 !
b11110 +
1#
